lykkelleloader/__init__.py
lykkelleloader/loadstockeod.py
lykkelleloader/loadstockhisteod.py
lykkelleloader-0.1.16.dist-info/LICENSE
lykkelleloader-0.1.16.dist-info/METADATA
lykkelleloader-0.1.16.dist-info/WHEEL
lykkelleloader-0.1.16.dist-info/top_level.txt
lykkelleloader-0.1.16.dist-info/RECORD
