Metadata-Version: 2.1
Name: lykkelleloader
Version: 0.1.16
Summary: Modules pertaining to loading stock and bond information from EODHistorical data
Home-page: https://dev.azure.com/lykkelle/Lykkelle/_git/Lykkellescripts
Author: Lykkelle Inc
Author-email: admin@lykkelle.com
License: UNKNOWN
Platform: UNKNOWN
Classifier: Programming Language :: Python :: 3
Classifier: License :: OSI Approved :: MIT License
Classifier: Operating System :: OS Independent
Requires-Python: >=3.6
